opencensus/__init__.py
opencensus/ext/__init__.py
opencensus/ext/httpx/__init__.py
opencensus/ext/httpx/trace.py
opencensus_ext_httpx-0.1.0.dist-info/METADATA
opencensus_ext_httpx-0.1.0.dist-info/WHEEL
opencensus_ext_httpx-0.1.0.dist-info/namespace_packages.txt
opencensus_ext_httpx-0.1.0.dist-info/top_level.txt
opencensus_ext_httpx-0.1.0.dist-info/RECORD
