Metadata-Version: 2.1
Name: opencensus-ext-httpx
Version: 0.1.0
Summary: OpenCensus HTTPX Integration
Home-page: UNKNOWN
Author: Michał Klich
Author-email: michal@klichx.dev
License: Apache-2.0
Platform: UNKNOWN
Classifier: Intended Audience :: Developers
Classifier: Development Status :: 3 - Alpha
Classifier: Intended Audience :: Developers
Classifier: License :: OSI Approved :: Apache Software License
Classifier: Programming Language :: Python
Classifier: Programming Language :: Python :: 3
Classifier: Programming Language :: Python :: 3.7
Classifier: Programming Language :: Python :: 3.8
Classifier: Programming Language :: Python :: 3.9
Requires-Dist: opencensus (<1.0.0,>=0.11.1)
Requires-Dist: httpx (>=0.22.0)
